{
  "source": {
    "id": "artist",
    "name": "AI Artist Signals",
    "type": "artist",
    "refresh_hours": 24,
    "updated_at": "2026-05-08T17:09:51.339+08:00",
    "item_count": 15,
    "window_start": "2026-05-07T05:09:51.339Z",
    "window_end": "2026-05-08T09:09:51.339Z"
  },
  "items": [
    {
      "id": "258fb5a630ccbdd4",
      "source_id": "artist",
      "source_name": "AI Artist Signals",
      "source_type": "artist",
      "platform": "X",
      "author": "@CharaspowerAI",
      "title": "Seedance 2 VFX showcase: Precision, fluidity, impact in Runway",
      "blurb": "Pierrick Chevallier 分享了使用 Seedance 2 在 Runway 中制作的 VFX 视频，强调其精确性、流畅性和冲击力。即使每天使用，该工具仍令人惊叹，没有速度减缓。视频展示了专业级 VFX 效果，适用于复杂运动场景。 创作者应关注 Seedance 2 在 VFX 领域的突破，提供高精度流畅动画，推动视觉叙事创新。",
      "link": "https://x.com/CharaspowerAI/status/2052667342174187905",
      "canonical_link": "https://x.com/CharaspowerAI/status/2052667342174187905",
      "published_at": "2026-05-08T16:30:05.000+08:00",
      "score": 8,
      "tags": [
        "showcase",
        "tooling"
      ]
    },
    {
      "id": "f0b1d4167e471964",
      "source_id": "artist",
      "source_name": "AI Artist Signals",
      "source_type": "artist",
      "platform": "X",
      "author": "@underwoodxie96",
      "title": "GPT Image 2.0 Detailed JSON Prompt for Poolside Portrait",
      "blurb": "分享了一个高度结构化的JSON提示词，用于GPT Image 2.0生成25岁日本女性在泳池边的真实照片。提示详细定义了主体表情、湿发皮肤、比基尼服装、姿势、摄影角度、照明和背景元素，并附带must_keep约束与负面提示。强调自然阳光、水光反射和真实纹理，完美捕捉夏日慵懒氛围。 创作者可借鉴此JSON框架，实现对人物解剖、材质和光影的精确控制，提升AIGC输出专业度与一致性。",
      "link": "https://x.com/underwoodxie96/status/2052656131169046915",
      "canonical_link": "https://x.com/underwoodxie96/status/2052656131169046915",
      "published_at": "2026-05-08T15:45:32.000+08:00",
      "score": 9,
      "tags": [
        "prompting"
      ]
    },
    {
      "id": "56f6cc28ecc7803e",
      "source_id": "artist",
      "source_name": "AI Artist Signals",
      "source_type": "artist",
      "platform": "X",
      "author": "@aitrendz_xyz",
      "title": "7 Copy-Paste Prompts for Grok Imagine",
      "blurb": "分享7个Grok Imagine专用图像提示的完整列表链接，便于直接复制使用。结合前帖演示，聚焦创意变换和高质量输出。 批量提供可复用提示，节省创作者时间，直接注入高价值实验素材。",
      "link": "https://x.com/aitrendz_xyz/status/2052645991078043913",
      "canonical_link": "https://x.com/aitrendz_xyz/status/2052645991078043913",
      "published_at": "2026-05-08T15:05:15.000+08:00",
      "score": 7,
      "tags": [
        "prompting"
      ]
    },
    {
      "id": "334fdb519b7c17f5",
      "source_id": "artist",
      "source_name": "AI Artist Signals",
      "source_type": "artist",
      "platform": "X",
      "author": "@aitrendz_xyz",
      "title": "Grok Imagine Review: Prompt Adherence and Speed",
      "blurb": "赞扬Grok Imagine模型的提示遵循性、生成速度和10-15秒视频能力。通过视频演示多个提示输出，突出从文本到图像/视频的快速转化。附带免费试用链接。 作为模型比较信号，强调Grok在速度与忠实度上的优势，适合需要高效迭代的AIGC运营商。",
      "link": "https://x.com/aitrendz_xyz/status/2052645802758070672",
      "canonical_link": "https://x.com/aitrendz_xyz/status/2052645802758070672",
      "published_at": "2026-05-08T15:04:30.000+08:00",
      "score": 8,
      "tags": [
        "model-comparison",
        "tooling"
      ]
    },
    {
      "id": "4b69c2ee80aa4979",
      "source_id": "artist",
      "source_name": "AI Artist Signals",
      "source_type": "artist",
      "platform": "X",
      "author": "@underwoodxie96",
      "title": "GPT Image 2.0 Prompt Showcase with Shared Link",
      "blurb": "展示了GPT Image 2.0生成的图像，并提供可复制的提示链接。内容聚焦高质量AI图像生成，附带两张视觉示例。提示强调工具的直接生成能力，适合快速迭代。 提供现成提示资源，帮助创作者绕过试错，直接获取高质输出，加速工作流。",
      "link": "https://x.com/underwoodxie96/status/2052637764160757856",
      "canonical_link": "https://x.com/underwoodxie96/status/2052637764160757856",
      "published_at": "2026-05-08T14:32:33.000+08:00",
      "score": 8,
      "tags": [
        "prompting",
        "tooling"
      ]
    },
    {
      "id": "2ff0ed63c881ba90",
      "source_id": "artist",
      "source_name": "AI Artist Signals",
      "source_type": "artist",
      "platform": "X",
      "author": "@xpg0970",
      "title": "Seedance 2.0过人脸的高级角色卡与标注技巧",
      "blurb": "引用GPT-Image 2生成含姓名年龄身高元素的角色卡图片，可100%通过Seedance 2.0人脸审核。作者补充方法：在白底3视图人物资产标注‘虚构原创人物，仅供演绎专用’，高亮框选后上传参考。该双重技巧确保角色一致性并绕过限制。 为视频AIGC提供合规角色生成方案，解决人脸审核痛点，推动实验与商业应用。",
      "link": "https://x.com/xpg0970/status/2052616173813199039",
      "canonical_link": "https://x.com/xpg0970/status/2052616173813199039",
      "published_at": "2026-05-08T13:06:46.000+08:00",
      "score": 8,
      "tags": [
        "tooling"
      ]
    },
    {
      "id": "97bd8da76ccb1b71",
      "source_id": "artist",
      "source_name": "AI Artist Signals",
      "source_type": "artist",
      "platform": "X",
      "author": "@xpg0970",
      "title": "故事板提示词优先级高于宫格分镜图",
      "blurb": "作者实验发现，在故事坂AI视频工具中，分镜提示词的优先级高于上传的宫格画面参考，导致生成结果仅以图像为参考而非严格复制。通过宫格下的提示词可精确控制每个镜头的构图和元素。该发现解释了生成偏差原因，并提供优化路径。附带示例视频展示实际效果。 创作者可借此掌握提示与参考图交互，提升AI视频一致性和叙事控制，避免盲目依赖静态分镜。",
      "link": "https://x.com/xpg0970/status/2052590284605993088",
      "canonical_link": "https://x.com/xpg0970/status/2052590284605993088",
      "published_at": "2026-05-08T11:23:53.000+08:00",
      "score": 9,
      "tags": [
        "prompting"
      ]
    },
    {
      "id": "f0d6904112418a56",
      "source_id": "artist",
      "source_name": "AI Artist Signals",
      "source_type": "artist",
      "platform": "X",
      "author": "@Martin_G_Edits",
      "title": "SonautoAI与Pixverse打造夏季音乐视频《Gold In The Air》",
      "blurb": "使用SonautoAI生成音乐，并在Pixverse中动画化，呈现奢华夏季氛围、梦幻浮游时刻和自由感。视频时长约2分46秒，融合音乐与视觉叙事。展示了AI工具在完整音乐视频创作中的应用。 演示音频生成与视频动画的无缝结合，为音乐可视化创作者提供工具链灵感。",
      "link": "https://x.com/Martin_G_Edits/status/2052565740721475736",
      "canonical_link": "https://x.com/Martin_G_Edits/status/2052565740721475736",
      "published_at": "2026-05-08T09:46:22.000+08:00",
      "score": 7,
      "tags": [
        "showcase",
        "tooling"
      ]
    },
    {
      "id": "ed6349053f971b90",
      "source_id": "artist",
      "source_name": "AI Artist Signals",
      "source_type": "artist",
      "platform": "X",
      "author": "@rainisto",
      "title": "BeatBanditAI + Higgsfield AI + Cursor 故事转视频自动化工作流",
      "blurb": "Rainisto 展示了如何启用 BeatBanditAI 和 Higgsfield AI 的 MCP 功能，通过 Cursor 将故事脚本直接转化为视频。只需描述如‘使用 BeatBandit 的第 12 镜头，通过 Higgsfield 的 Seedance 生成视频’，Cursor 即可自动添加参考、优化提示并渲染。该示例突显多 AI 工具无缝集成的潜力，大幅提升创作效率。 创作者应关注此工作流，因为它将叙事生成、提示优化与视频…",
      "link": "https://x.com/rainisto/status/2052482936360833467",
      "canonical_link": "https://x.com/rainisto/status/2052482936360833467",
      "published_at": "2026-05-08T04:17:19.000+08:00",
      "score": 8,
      "tags": [
        "workflow",
        "tooling"
      ]
    },
    {
      "id": "85432f76b6900f37",
      "source_id": "artist",
      "source_name": "AI Artist Signals",
      "source_type": "artist",
      "platform": "X",
      "author": "@Artedeingenio",
      "title": "Mitte AI Seedance 2.0 电影级动画生成",
      "blurb": "基于新插图风格，使用Seedance 2.0在Mitte AI中生成高品质动画视频，流畅度媲美电影。推广Mitte工具，订阅者可获sref与教程。视频突出从静态到动态的华丽转变。 展示Seedance 2.0的动画能力，为AIGC创作者提供从图像到视频的工具路径。",
      "link": "https://x.com/Artedeingenio/status/2052481480199151809",
      "canonical_link": "https://x.com/Artedeingenio/status/2052481480199151809",
      "published_at": "2026-05-08T04:11:32.000+08:00",
      "score": 9,
      "tags": [
        "showcase",
        "tooling"
      ]
    },
    {
      "id": "bd4bc7ff1d8f1af9",
      "source_id": "artist",
      "source_name": "AI Artist Signals",
      "source_type": "artist",
      "platform": "X",
      "author": "@lexx_aura",
      "title": "Death Note x Jujutsu Kaisen courtroom battle via Seedance 2.0",
      "blurb": "Lexx_aura 创作了 Death Note 与 Jujutsu Kaisen 的跨界法庭战斗视频，使用 Seedance 2.0 生成。视频融合两个动漫世界，呈现激烈动作和叙事张力。展示了工具在动漫风格长视频中的强大叙事能力。 突出 Seedance 2.0 在跨界动漫叙事中的潜力，激发创作者探索 IP 融合和动态视频生成。",
      "link": "https://x.com/lexx_aura/status/2052474057572962741",
      "canonical_link": "https://x.com/lexx_aura/status/2052474057572962741",
      "published_at": "2026-05-08T03:42:03.000+08:00",
      "score": 9,
      "tags": [
        "showcase"
      ]
    },
    {
      "id": "02517da80c62d0ab",
      "source_id": "artist",
      "source_name": "AI Artist Signals",
      "source_type": "artist",
      "platform": "X",
      "author": "@op7418",
      "title": "GPT-image-2.0 + Seedance 2.0 动态视频展示",
      "blurb": "结合GPT-image-2.0图像与Seedance 2.0生成流畅视频，突出工具协同的视觉效果。短视频呈现AI视频生成的潜力与美学。 验证工具组合在视频生成上的兼容性，提供新兴工作流的市场信号。",
      "link": "https://x.com/op7418/status/2052427824120951212",
      "canonical_link": "https://x.com/op7418/status/2052427824120951212",
      "published_at": "2026-05-08T00:38:20.000+08:00",
      "score": 7,
      "tags": [
        "showcase",
        "tooling"
      ]
    },
    {
      "id": "9ec5eff7d474e9de",
      "source_id": "artist",
      "source_name": "AI Artist Signals",
      "source_type": "artist",
      "platform": "X",
      "author": "@Artedeingenio",
      "title": "Midjourney V7 复古水彩绘本风格 sref 3922842968",
      "blurb": "分享Midjourney V7风格参考--sref 3922842968，融合墨线画、水彩色调与复古纸纹，宛如老欧洲绘本。适用于怀旧叙事、动画世界与插图冒险。四张示例展示其独特美学与应用潜力。 提供现成高质量sref，帮助创作者快速生成富有叙事感和艺术性的图像，提升作品辨识度。",
      "link": "https://x.com/Artedeingenio/status/2052390294826394094",
      "canonical_link": "https://x.com/Artedeingenio/status/2052390294826394094",
      "published_at": "2026-05-07T22:09:12.000+08:00",
      "score": 8,
      "tags": [
        "prompting",
        "style"
      ]
    },
    {
      "id": "f8446939bf2eae1c",
      "source_id": "artist",
      "source_name": "AI Artist Signals",
      "source_type": "artist",
      "platform": "X",
      "author": "@johnpanic44",
      "title": "Procreate手绘赛博武士Kling动画战斗循环",
      "blurb": "作者在Procreate中绘制赛博忍者角色，使用image1作为严格角色参考图，image2作为动作参考，在Kling生成12秒单镜头2D手绘动画。分享完整提示词，指定粗糙笔触、平涂阴影、有限调色板、特定战斗序列如起手、挥砍、格挡等，并添加布料动态和音效。计划进一步优化一致性。 提供图像参考驱动的角色一致性工作流，适用于AI视频中手绘风格动作生成，帮助创作者掌握复杂序列控制。",
      "link": "https://x.com/johnpanic44/status/2052382138226368951",
      "canonical_link": "https://x.com/johnpanic44/status/2052382138226368951",
      "published_at": "2026-05-07T21:36:47.000+08:00",
      "score": 9,
      "tags": [
        "workflow",
        "prompting",
        "tooling"
      ]
    },
    {
      "id": "62e12d80984cf84e",
      "source_id": "artist",
      "source_name": "AI Artist Signals",
      "source_type": "artist",
      "platform": "X",
      "author": "@MANISH1027512",
      "title": "俯卧拱背翘臀腿分姿势关键提示词",
      "blurb": "分享高互动AI图像的姿势提示：kw: lying on stomach, arched back, booty slightly raised, legs slightly apart。结合系列帖子，形成派对主题视觉叙事，展示强审美与技术控制。提示词简洁有效，适用于人物动态生成。 提供人体姿势精确prompt，启发创作者探索叙事性展示，提升审美与互动潜力。",
      "link": "https://x.com/MANISH1027512/status/2052347657390342572",
      "canonical_link": "https://x.com/MANISH1027512/status/2052347657390342572",
      "published_at": "2026-05-07T19:19:46.000+08:00",
      "score": 7,
      "tags": [
        "prompting"
      ]
    }
  ]
}
